gadgetlib/__init__.py
gadgetlib/shipstation.py
gadgetlib/tools.py
gadgetlib-0.1.1.dist-info/METADATA
gadgetlib-0.1.1.dist-info/WHEEL
gadgetlib-0.1.1.dist-info/licenses/LICENSE
gadgetlib-0.1.1.dist-info/RECORD
