Metadata-Version: 2.4
Name: gadgetlib
Version: 0.1.1
Summary: A collection of tools for personal use
Author-email: Kyle Dvorak <kylodss@gmail.com>
License-File: LICENSE
Classifier: License :: OSI Approved :: MIT License
Classifier: Operating System :: OS Independent
Classifier: Programming Language :: Python :: 3
Requires-Python: >=3.8
